ConservedWaterSearch/__init__.py
ConservedWaterSearch/hydrogen_orientation.py
ConservedWaterSearch/utils.py
ConservedWaterSearch/water_clustering.py
ConservedWaterSearch-0.4.1.dist-info/LICENSE
ConservedWaterSearch-0.4.1.dist-info/METADATA
ConservedWaterSearch-0.4.1.dist-info/WHEEL
ConservedWaterSearch-0.4.1.dist-info/top_level.txt
ConservedWaterSearch-0.4.1.dist-info/RECORD
