Metadata-Version: 2.1
Name: ConservedWaterSearch
Version: 0.4.1
Summary: Conserved water search is a tool for finding conserved water molecules from MD trajectories.
Author: Domagoj Fijan, Marko Jukic, Urban Bren
Author-email: Jelena Tosovic <jecat_90@live.com>
License: BSD 3-Clause License
Project-URL: Homepage, https://github.com/JecaTosovic/ConservedWaterSearch
Project-URL: Documentation, https://ConservedWaterSearch.readthedocs.io/
Project-URL: Source, https://github.com/JecaTosovic/ConservedWaterSearch
Project-URL: Issue, https://github.com/JecaTosovic/ConservedWaterSearch/issues
Keywords: simulation,analysis,molecular dynamics,biosimulation,conserved water
Classifier: Development Status :: 4 - Beta
Classifier: Intended Audience :: Science/Research
Classifier: Topic :: Scientific/Engineering :: Chemistry
Classifier: Topic :: Scientific/Engineering :: Bio-Informatics
Classifier: Programming Language :: Python :: 3.9
Classifier: Programming Language :: Python :: 3.10
Classifier: Programming Language :: Python :: 3.11
Classifier: Programming Language :: Python :: 3.12
Requires-Python: >=3.9
License-File: LICENSE
Requires-Dist: numpy >=1.22
Requires-Dist: scikit-learn >=1.3
